[
        {
            "No": "001",
            "MyDate": "星期一",
            "MyTime": "08:00~09:00",
            "Task": "垃圾及資源回收物處理並清潔垃圾場",
            "Owner": "陳東猛；陳靜風；武氏惠；黃氏銀"
        },
        {
            "No": "002",
            "MyDate": "星期一",
            "MyTime": "09:00~09:30",
            "Task": "倒垃圾、外圍及中庭打掃",
            "Owner": "陳東猛；陳靜風；武氏惠；黃氏銀"
        },
        {
            "No": "003",
            "MyDate": "星期一",
            "MyTime": "09:30~10:00",
            "Task": "大廳及廁所清潔",
            "Owner": "武氏惠；黃氏銀"
        },
        {
            "No": "004",
            "MyDate": "星期一",
            "MyTime": "10:00~10:20",
            "Task": "各棟1樓~B3F梯廳及廁所清潔",
            "Owner": "陳東猛C棟；陳靜風B棟；武氏惠F棟；黃氏銀H棟"
        },
        {
            "No": "005",
            "MyDate": "星期一",
            "MyTime": "10:30~11:30",
            "Task": "公設清潔(健身房、交誼廳、小酒吧、兒童遊戲室及KTV)",
            "Owner": "陳東猛；陳靜風；武氏惠；黃氏銀"
        },
        {
            "No": "006",
            "MyDate": "星期一",
            "MyTime": "11:30~12:00",
            "Task": "停車場角落、燈罩蜘蛛絲清除",
            "Owner": "陳東猛B2；陳靜風B3；武氏惠B1；黃氏銀B1"
        },
        {
            "No": "007",
            "MyDate": "星期一",
            "MyTime": "13:00~13:30",
            "Task": "資源回收場整理",
            "Owner": "陳東猛；陳靜風；武氏惠；黃氏銀"
        },
        {
            "No": "008",
            "MyDate": "星期一",
            "MyTime": "13:30~14:00",
            "Task": "腳踏車位(1~53)清掃",
            "Owner": "陳東猛；陳靜風；武氏惠；黃氏銀"
        },
        {
            "No": "009",
            "MyDate": "星期一",
            "MyTime": "14:00~15:00",
            "Task": "停車場角落、燈罩蜘蛛絲清除",
            "Owner": "陳東猛B2；陳靜風B3；武氏惠B1；黃氏銀B1"
        },
        {
            "No": "010",
            "MyDate": "星期一",
            "MyTime": "15:10~16:00",
            "Task": "R樓清掃、雜草拔除、落水孔清污、安全梯及扶手清潔",
            "Owner": "陳東猛CD棟；陳靜風AB棟；武氏惠EF棟；黃氏銀GH棟"
        },
        {
            "No": "011",
            "MyDate": "星期一",
            "MyTime": "16:00~16:30",
            "Task": "R樓清掃、雜草拔除、落水孔清污、安全梯及扶手清潔",
            "Owner": "陳東猛CD棟；陳靜風AB棟；武氏惠EF棟；黃氏銀GH棟"
        },
        {
            "No": "012",
            "MyDate": "星期一",
            "MyTime": "16:30~16:50",
            "Task": "外圍、中庭巡掃",
            "Owner": "陳東猛；陳靜風；武氏惠；黃氏銀"
        },
        {
            "No": "013",
            "MyDate": "星期一",
            "MyTime": "16:50~17:00",
            "Task": "清潔用具清洗",
            "Owner": "陳東猛；陳靜風；武氏惠；黃氏銀"
        },
        {
            "No": "014",
            "MyDate": "星期二",
            "MyTime": "08:00~09:00",
            "Task": "垃圾及資源回收物處理並清潔垃圾場",
            "Owner": "陳東猛；陳靜風；武氏惠"
        },
        {
            "No": "015",
            "MyDate": "星期二",
            "MyTime": "09:00~09:30",
            "Task": "外圍及中庭打掃",
            "Owner": "陳東猛；陳靜風；武氏惠"
        },
        {
            "No": "016",
            "MyDate": "星期二",
            "MyTime": "09:30~10:00",
            "Task": "大廳及廁所清潔",
            "Owner": "武氏惠"
        },
        {
            "No": "017",
            "MyDate": "星期二",
            "MyTime": "10:00~10:20",
            "Task": "各棟1樓~B3F梯廳及廁所清潔",
            "Owner": "陳東猛D棟；陳靜風A棟；武氏惠E棟"
        },
        {
            "No": "018",
            "MyDate": "星期二",
            "MyTime": "10:30~11:30",
            "Task": "公設巡檢清潔、電梯清潔(壁面、按鍵及車廂內部)",
            "Owner": "陳東猛D棟；陳靜風A棟；武氏惠E棟"
        },
        {
            "No": "019",
            "MyDate": "星期二",
            "MyTime": "11:30~12:00",
            "Task": "停車場巡檢(281~310汽、機車位)清潔",
            "Owner": "陳東猛B2；陳靜風B3；武氏惠B1"
        },
        {
            "No": "020",
            "MyDate": "星期二",
            "MyTime": "13:00~13:30",
            "Task": "資源回收場整理",
            "Owner": "陳東猛；陳靜風；武氏惠"
        },
        {
            "No": "021",
            "MyDate": "星期二",
            "MyTime": "13:30~14:00",
            "Task": "廚餘整理傾倒廚餘",
            "Owner": "陳東猛；陳靜風；武氏惠"
        },
        {
            "No": "022",
            "MyDate": "星期二",
            "MyTime": "14:00~15:00",
            "Task": "各棟(R~9)樓層梯廳地板、壁面、窗框、玻璃清潔",
            "Owner": "陳東猛D棟；陳靜風A棟；武氏惠E棟"
        },
        {
            "No": "023",
            "MyDate": "星期二",
            "MyTime": "15:10~16:00",
            "Task": "各棟(8~2)樓層梯廳地板、壁面、窗框、玻璃清潔",
            "Owner": "陳東猛D棟；陳靜風A棟；武氏惠E棟"
        },
        {
            "No": "024",
            "MyDate": "星期二",
            "MyTime": "16:00~16:30",
            "Task": "執行特殊交辦工項",
            "Owner": "陳東猛D棟；陳靜風A棟；武氏惠E棟"
        },
        {
            "No": "025",
            "MyDate": "星期二",
            "MyTime": "16:30~16:50",
            "Task": "外圍、中庭巡掃",
            "Owner": "陳東猛；陳靜風；武氏惠"
        },
        {
            "No": "026",
            "MyDate": "星期二",
            "MyTime": "16:50~17:00",
            "Task": "清潔用具清洗",
            "Owner": "陳東猛；陳靜風；武氏惠"
        },
        {
            "No": "027",
            "MyDate": "星期三",
            "MyTime": "08:00~09:00",
            "Task": "垃圾及資源回收物處理並清潔垃圾場",
            "Owner": "陳東猛；陳靜風；武氏惠；黃氏銀"
        },
        {
            "No": "028",
            "MyDate": "星期三",
            "MyTime": "09:00~09:30",
            "Task": "外圍及中庭打掃",
            "Owner": "陳東猛；陳靜風；武氏惠；黃氏銀"
        },
        {
            "No": "029",
            "MyDate": "星期三",
            "MyTime": "09:30~10:00",
            "Task": "大廳及廁所清潔",
            "Owner": "武氏惠；黃氏銀"
        },
        {
            "No": "030",
            "MyDate": "星期三",
            "MyTime": "10:00~10:20",
            "Task": "各棟1樓~B3F梯廳及廁所清潔",
            "Owner": "陳東猛C棟；陳靜風B棟；武氏惠F棟；黃氏銀G棟"
        },
        {
            "No": "031",
            "MyDate": "星期三",
            "MyTime": "10:30~11:30",
            "Task": "公設巡檢清潔、電梯清潔(壁面、按鍵及車廂內部)",
            "Owner": "陳東猛C棟；陳靜風B棟；武氏惠F棟；黃氏銀G棟"
        },
        {
            "No": "032",
            "MyDate": "星期三",
            "MyTime": "11:30~12:00",
            "Task": "停車場巡檢(311~346汽、機車位)清潔",
            "Owner": "陳東猛B2；陳靜風B3；武氏惠B1；黃氏銀B1"
        },
        {
            "No": "033",
            "MyDate": "星期三",
            "MyTime": "13:00~13:30",
            "Task": "資源回收場整理",
            "Owner": "陳東猛B2；陳靜風B3；武氏惠B1；黃氏銀B1"
        },
        {
            "No": "034",
            "MyDate": "星期三",
            "MyTime": "13:30~14:00",
            "Task": "停車場巡檢(001~040汽、機車位)清潔"
        },
        {
            "No": "035",
            "MyDate": "星期三",
            "MyTime": "14:00~15:00",
            "Task": "各棟(R~9)樓層梯廳地板、壁面、窗框、玻璃清潔",
            "Owner": "陳東猛C棟；陳靜風B棟；武氏惠F棟；黃氏銀G棟"
        },
        {
            "No": "036",
            "MyDate": "星期三",
            "MyTime": "15:10~16:00",
            "Task": "各棟(8~2)樓層梯廳地板、壁面、窗框、玻璃清潔",
            "Owner": "陳東猛C棟；陳靜風B棟；武氏惠F棟；黃氏銀G棟"
        },
        {
            "No": "037",
            "MyDate": "星期三",
            "MyTime": "16:00~16:30",
            "Task": "執行特殊交辦工項",
            "Owner": "陳東猛C棟；陳靜風B棟；武氏惠F棟；黃氏銀G棟"
        },
        {
            "No": "038",
            "MyDate": "星期三",
            "MyTime": "16:30~16:50",
            "Task": "外圍、中庭巡掃",
            "Owner": "陳東猛；陳靜風；武氏惠；黃氏銀"
        },
        {
            "No": "039",
            "MyDate": "星期三",
            "MyTime": "16:50~17:00",
            "Task": "清潔用具清洗",
            "Owner": "陳東猛；陳靜風；武氏惠；黃氏銀"
        },
        {
            "No": "040",
            "MyDate": "星期四",
            "MyTime": "08:00~09:00",
            "Task": "垃圾及資源回收物處理並清潔垃圾場",
            "Owner": "陳靜風；武氏惠；黃氏銀"
        },
        {
            "No": "041",
            "MyDate": "星期四",
            "MyTime": "09:00~09:30",
            "Task": "倒垃圾、外圍及中庭打掃",
            "Owner": "陳靜風；武氏惠；黃氏銀"
        },
        {
            "No": "042",
            "MyDate": "星期四",
            "MyTime": "09:30~10:00",
            "Task": "大廳及廁所清潔",
            "Owner": "武氏惠；黃氏銀"
        },
        {
            "No": "043",
            "MyDate": "星期四",
            "MyTime": "10:00~10:20",
            "Task": "各棟1樓~B3F梯廳及廁所清潔",
            "Owner": "陳靜風A棟；武氏惠E棟；黃氏銀H棟"
        },
        {
            "No": "044",
            "MyDate": "星期四",
            "MyTime": "10:30~11:30",
            "Task": "公設巡檢清潔、電梯清潔(壁面、按鍵及車廂內部)",
            "Owner": "陳靜風A棟；武氏惠E棟；黃氏銀H棟"
        },
        {
            "No": "045",
            "MyDate": "星期四",
            "MyTime": "11:30~12:00",
            "Task": "停車場巡檢(041~070汽、機車位)清潔",
            "Owner": "陳靜風B3；武氏惠B1；黃氏銀B1"
        },
        {
            "No": "046",
            "MyDate": "星期四",
            "MyTime": "13:00~13:30",
            "Task": "資源回收場整理，廠商回收日",
            "Owner": "陳靜風；武氏惠；黃氏銀"
        },
        {
            "No": "047",
            "MyDate": "星期四",
            "MyTime": "13:30~14:00",
            "Task": "資源回收場整理，廠商回收日",
            "Owner": "陳靜風；武氏惠；黃氏銀"
        },
        {
            "No": "048",
            "MyDate": "星期四",
            "MyTime": "14:00~15:00",
            "Task": "各棟(R~9)樓層梯廳地板、壁面、窗框、玻璃清潔",
            "Owner": "陳靜風A棟；武氏惠E棟；黃氏銀H棟"
        },
        {
            "No": "049",
            "MyDate": "星期四",
            "MyTime": "15:10~16:00",
            "Task": "各棟(8~2)樓層梯廳地板、壁面、窗框、玻璃清潔",
            "Owner": "陳靜風A棟；武氏惠E棟；黃氏銀H棟"
        },
        {
            "No": "050",
            "MyDate": "星期四",
            "MyTime": "16:00~16:30",
            "Task": "執行特殊交辦工項",
            "Owner": "陳靜風A棟；武氏惠E棟；黃氏銀H棟"
        },
        {
            "No": "051",
            "MyDate": "星期四",
            "MyTime": "16:30~16:50",
            "Task": "外圍、中庭巡掃",
            "Owner": "陳靜風；武氏惠；黃氏銀"
        },
        {
            "No": "052",
            "MyDate": "星期四",
            "MyTime": "16:50~17:00",
            "Task": "清潔用具清洗",
            "Owner": "陳靜風；武氏惠；黃氏銀"
        },
        {
            "No": "053",
            "MyDate": "星期五",
            "MyTime": "08:00~09:00",
            "Task": "垃圾及資源回收物處理並清潔垃圾場",
            "Owner": "陳東猛；武氏惠；黃氏銀"
        },
        {
            "No": "054",
            "MyDate": "星期五",
            "MyTime": "09:00~09:30",
            "Task": "外圍及中庭打掃",
            "Owner": "陳東猛；武氏惠；黃氏銀"
        },
        {
            "No": "055",
            "MyDate": "星期五",
            "MyTime": "09:30~10:00",
            "Task": "大廳及廁所清潔",
            "Owner": "武氏惠；黃氏銀"
        },
        {
            "No": "056",
            "MyDate": "星期五",
            "MyTime": "10:00~10:20",
            "Task": "各棟1樓~B3F梯廳及廁所清潔",
            "Owner": "陳東猛D棟；武氏惠F棟；黃氏銀G棟"
        },
        {
            "No": "057",
            "MyDate": "星期五",
            "MyTime": "10:30~11:30",
            "Task": "公設巡檢清潔、電梯清潔(壁面、按鍵及車廂內部)",
            "Owner": "陳東猛D棟；武氏惠F棟；黃氏銀G棟"
        },
        {
            "No": "058",
            "MyDate": "星期五",
            "MyTime": "11:30~12:00",
            "Task": "停車場巡檢(071~100汽、機車位)清潔",
            "Owner": "陳東猛B2；武氏惠B1；黃氏銀B1"
        },
        {
            "No": "059",
            "MyDate": "星期五",
            "MyTime": "13:00~13:30",
            "Task": "資源回收場整理",
            "Owner": "陳東猛；武氏惠；黃氏銀"
        },
        {
            "No": "060",
            "MyDate": "星期五",
            "MyTime": "13:30~14:00",
            "Task": "停車場巡檢(101~130汽、機車位)清潔",
            "Owner": "陳東猛B2；武氏惠B1；黃氏銀B1"
        },
        {
            "No": "061",
            "MyDate": "星期五",
            "MyTime": "14:00~15:00",
            "Task": "各棟(R~9)樓層梯廳地板、壁面、窗框、玻璃清潔",
            "Owner": "陳東猛D棟；武氏惠F棟；黃氏銀G棟"
        },
        {
            "No": "062",
            "MyDate": "星期五",
            "MyTime": "15:10~16:00",
            "Task": "各棟(8~2)樓層梯廳地板、壁面、窗框、玻璃清潔",
            "Owner": "陳東猛D棟；武氏惠F棟；黃氏銀G棟"
        },
        {
            "No": "063",
            "MyDate": "星期五",
            "MyTime": "16:00~16:30",
            "Task": "執行特殊交辦工項",
            "Owner": "陳東猛D棟；武氏惠F棟；黃氏銀G棟"
        },
        {
            "No": "064",
            "MyDate": "星期五",
            "MyTime": "16:30~16:50",
            "Task": "外圍、中庭巡掃",
            "Owner": "陳東猛；武氏惠；黃氏銀"
        },
        {
            "No": "065",
            "MyDate": "星期五",
            "MyTime": "16:50~17:00",
            "Task": "清潔用具清洗",
            "Owner": "陳東猛；武氏惠；黃氏銀"
        },
        {
            "No": "066",
            "MyDate": "星期六",
            "MyTime": "08:00~09:00",
            "Task": "垃圾及資源回收物處理並清潔垃圾場",
            "Owner": "陳東猛；陳靜風"
        },
        {
            "No": "067",
            "MyDate": "星期六",
            "MyTime": "09:00~09:30",
            "Task": "外圍及中庭打掃",
            "Owner": "陳東猛；陳靜風"
        },
        {
            "No": "068",
            "MyDate": "星期六",
            "MyTime": "09:30~10:00",
            "Task": "大廳及廁所清潔",
            "Owner": "陳東猛；陳靜風"
        },
        {
            "No": "069",
            "MyDate": "星期六",
            "MyTime": "10:00~10:20",
            "Task": "各棟1樓~B3F梯廳及廁所清潔",
            "Owner": "陳東猛C棟；陳靜風B棟"
        },
        {
            "No": "070",
            "MyDate": "星期六",
            "MyTime": "10:30~11:30",
            "Task": "公設巡檢清潔、電梯清潔(壁面、按鍵及車廂內部)",
            "Owner": "陳東猛C棟；陳靜風B棟"
        },
        {
            "No": "071",
            "MyDate": "星期六",
            "MyTime": "11:30~12:00",
            "Task": "停車場巡檢(131~150汽、機車位)清潔",
            "Owner": "陳東猛B2；陳靜風B3"
        },
        {
            "No": "072",
            "MyDate": "星期六",
            "MyTime": "13:00~13:30",
            "Task": "資源回收場整理，廠商回收日",
            "Owner": "陳東猛；陳靜風"
        },
        {
            "No": "073",
            "MyDate": "星期六",
            "MyTime": "13:30~14:00",
            "Task": "資源回收場整理，廠商回收日",
            "Owner": "陳東猛；陳靜風"
        },
        {
            "No": "074",
            "MyDate": "星期六",
            "MyTime": "14:00~15:00",
            "Task": "各棟(R~9)樓層梯廳地板、壁面、窗框、玻璃清潔",
            "Owner": "陳東猛C棟；陳靜風B棟"
        },
        {
            "No": "075",
            "MyDate": "星期六",
            "MyTime": "15:10~16:00",
            "Task": "各棟(8~2)樓層梯廳地板、壁面、窗框、玻璃清潔",
            "Owner": "陳東猛C棟；陳靜風B棟"
        },
        {
            "No": "076",
            "MyDate": "星期六",
            "MyTime": "16:00~16:30",
            "Task": "執行特殊交辦工項",
            "Owner": "陳東猛C棟；陳靜風B棟"
        },
        {
            "No": "077",
            "MyDate": "星期六",
            "MyTime": "16:30~16:50",
            "Task": "外圍、中庭巡掃",
            "Owner": "陳東猛；陳靜風"
        },
        {
            "No": "078",
            "MyDate": "星期六",
            "MyTime": "16:50~17:00",
            "Task": "清潔用具清洗",
            "Owner": "陳東猛；陳靜風"
        },
        {
            "No": "079",
            "MyDate": "星期日",
            "MyTime": "08:00~09:00",
            "Task": "垃圾及資源回收物處理並清潔垃圾場",
            "Owner": "陳靜風；黃氏銀"
        },
        {
            "No": "080",
            "MyDate": "星期日",
            "MyTime": "09:00~09:30",
            "Task": "外圍及中庭打掃",
            "Owner": "陳靜風；黃氏銀"
        },
        {
            "No": "081",
            "MyDate": "星期日",
            "MyTime": "09:30~10:00",
            "Task": "大廳及廁所清潔",
            "Owner": "黃氏銀"
        },
        {
            "No": "082",
            "MyDate": "星期日",
            "MyTime": "10:00~10:20",
            "Task": "各棟1樓~B3F梯廳及廁所清潔",
            "Owner": "陳靜風A棟；黃氏銀H棟"
        },
        {
            "No": "083",
            "MyDate": "星期日",
            "MyTime": "10:30~11:30",
            "Task": "公設巡檢清潔、電梯清潔(壁面、按鍵及車廂內部)",
            "Owner": "陳靜風A棟；黃氏銀H棟"
        },
        {
            "No": "084",
            "MyDate": "星期日",
            "MyTime": "11:30~12:00",
            "Task": "停車場巡檢(151~170汽、機車位)清潔",
            "Owner": "陳靜風B3；黃氏銀B1"
        },
        {
            "No": "085",
            "MyDate": "星期日",
            "MyTime": "13:00~13:30",
            "Task": "資源回收場整理",
            "Owner": "陳靜風；黃氏銀"
        },
        {
            "No": "086",
            "MyDate": "星期日",
            "MyTime": "13:30~14:00",
            "Task": "停車場巡檢(171~190汽、機車位)清潔",
            "Owner": "陳靜風B3；黃氏銀B1"
        },
        {
            "No": "087",
            "MyDate": "星期日",
            "MyTime": "14:00~15:00",
            "Task": "各棟(R~9)樓層梯廳地板、壁面、窗框、玻璃清潔",
            "Owner": "陳靜風A棟；黃氏銀H棟"
        },
        {
            "No": "088",
            "MyDate": "星期日",
            "MyTime": "15:10~16:00",
            "Task": "各棟(8~2)樓層梯廳地板、壁面、窗框、玻璃清潔",
            "Owner": "陳靜風A棟；黃氏銀H棟"
        },
        {
            "No": "089",
            "MyDate": "星期日",
            "MyTime": "16:00~16:30",
            "Task": "執行特殊交辦工項",
            "Owner": "陳靜風A棟；黃氏銀H棟"
        },
        {
            "No": "090",
            "MyDate": "星期日",
            "MyTime": "16:30~16:50",
            "Task": "外圍、中庭巡掃",
            "Owner": "陳靜風；黃氏銀"
        },
        {
            "No": "091",
            "MyDate": "星期日",
            "MyTime": "16:50~17:00",
            "Task": "清潔用具清洗",
            "Owner": "陳靜風；黃氏銀"
        }
    ]